airtableio/__init__.py
airtableio/airtable.py
airtableio/api.py
airtableio/client.py
airtableio/exceptions.py
airtableio/helpers.py
airtableio-0.1.2.dist-info/LICENSE
airtableio-0.1.2.dist-info/METADATA
airtableio-0.1.2.dist-info/WHEEL
airtableio-0.1.2.dist-info/top_level.txt
airtableio-0.1.2.dist-info/RECORD
