Metadata-Version: 2.1
Name: airtableio
Version: 0.1.2
Summary: Async wrapper for airtable.
Home-page: https://github.com/uleague/airtableio
Author: Evgenii Petrovich
Author-email: parapheen6@gmail.com
License: MIT
Platform: UNKNOWN
Classifier: License :: OSI Approved :: MIT License
Classifier: Programming Language :: Python
Classifier: Programming Language :: Python :: 3
Classifier: Programming Language :: Python :: 3.6
Classifier: Programming Language :: Python :: Implementation :: CPython
Classifier: Programming Language :: Python :: Implementation :: PyPy
Requires-Python: >=3.6.0
Requires-Dist: aiohttp
